backtestbuddy/__init__.py
backtestbuddy/backtest/__init__.py
backtestbuddy/backtest/sport_backtest.py
backtestbuddy/metrics/__init__.py
backtestbuddy/metrics/sport_metrics.py
backtestbuddy/plots/__init__.py
backtestbuddy/plots/sport_plots.py
backtestbuddy/strategies/__init__.py
backtestbuddy/strategies/sport_strategies.py
backtestbuddy-0.1.12.dist-info/METADATA
backtestbuddy-0.1.12.dist-info/WHEEL
backtestbuddy-0.1.12.dist-info/licenses/LICENSE
backtestbuddy-0.1.12.dist-info/RECORD
