Metadata-Version: 2.4
Name: backtestbuddy
Version: 0.1.12
Summary: A flexible backtesting framework for trading and betting strategies
Project-URL: Homepage, https://github.com/Pacman1984/backtestbuddy
Project-URL: Documentation, https://github.com/Pacman1984/backtestbuddy
Project-URL: Repository, https://github.com/Pacman1984/backtestbuddy
Project-URL: Issues, https://github.com/Pacman1984/backtestbuddy/issues
Author: Sebastian Pachl
License: MIT License
License-File: LICENSE
Keywords: backtesting,betting,finance,quantitative-finance,sports-betting,trading
Classifier: Development Status :: 4 - Beta
Classifier: Intended Audience :: Developers
Classifier: Intended Audience :: Financial and Insurance Industry
Classifier: License :: OSI Approved :: MIT License
Classifier: Operating System :: OS Independent
Classifier: Programming Language :: Python :: 3
Classifier: Programming Language :: Python :: 3.9
Classifier: Programming Language :: Python :: 3.10
Classifier: Programming Language :: Python :: 3.11
Classifier: Programming Language :: Python :: 3.12
Classifier: Topic :: Office/Business :: Financial :: Investment
Classifier: Topic :: Scientific/Engineering :: Artificial Intelligence
Requires-Python: >=3.9
Requires-Dist: matplotlib>=3.5.0
Requires-Dist: nbformat>=5.0.0
Requires-Dist: numpy>=1.26.0
Requires-Dist: pandas>=1.3.0
Requires-Dist: plotly>=5.0.0
Requires-Dist: scikit-learn>=1.0.0
Requires-Dist: scipy>=1.7.0
Provides-Extra: all
Requires-Dist: black>=23.0; extra == 'all'
Requires-Dist: flake8>=6.0; extra == 'all'
Requires-Dist: isort>=5.12; extra == 'all'
Requires-Dist: mkdocs-awesome-pages-plugin>=2.9.0; extra == 'all'
Requires-Dist: mkdocs-material>=9.0; extra == 'all'
Requires-Dist: mkdocs>=1.5.0; extra == 'all'
Requires-Dist: mypy>=1.0; extra == 'all'
Requires-Dist: pytest-cov>=4.0; extra == 'all'
Requires-Dist: pytest>=7.0; extra == 'all'
Requires-Dist: ruff>=0.1.0; extra == 'all'
Provides-Extra: dev
Requires-Dist: black>=23.0; extra == 'dev'
Requires-Dist: flake8>=6.0; extra == 'dev'
Requires-Dist: isort>=5.12; extra == 'dev'
Requires-Dist: mypy>=1.0; extra == 'dev'
Requires-Dist: pytest-cov>=4.0; extra == 'dev'
Requires-Dist: pytest>=7.0; extra == 'dev'
Requires-Dist: ruff>=0.1.0; extra == 'dev'
Provides-Extra: docs
Requires-Dist: mkdocs-awesome-pages-plugin>=2.9.0; extra == 'docs'
Requires-Dist: mkdocs-material>=9.0; extra == 'docs'
Requires-Dist: mkdocs>=1.5.0; extra == 'docs'
Provides-Extra: test
Requires-Dist: pytest-cov>=4.0; extra == 'test'
Requires-Dist: pytest>=7.0; extra == 'test'
